stockDataPlots/__init__.py
stockDataPlots/_modidx.py
stockDataPlots/structureData.py
stockDataPlots-0.0.7.dist-info/LICENSE
stockDataPlots-0.0.7.dist-info/METADATA
stockDataPlots-0.0.7.dist-info/WHEEL
stockDataPlots-0.0.7.dist-info/entry_points.txt
stockDataPlots-0.0.7.dist-info/top_level.txt
stockDataPlots-0.0.7.dist-info/RECORD
