Metadata-Version: 2.1
Name: stockDataPlots
Version: 0.0.7
Summary: Scraping stock information from Yahoo Finance and presenting it in a beautiful way.
Home-page: https://github.com/kaiguender/stockDataPlots
Author: kaiguender
Author-email: kai.guender@yahoo.de
License: Apache Software License 2.0
Keywords: nbdev jupyter notebook python
Platform: UNKNOWN
Classifier: Development Status :: 4 - Beta
Classifier: Intended Audience :: Developers
Classifier: Natural Language :: English
Classifier: Programming Language :: Python :: 3.7
Classifier: Programming Language :: Python :: 3.8
Classifier: Programming Language :: Python :: 3.9
Classifier: Programming Language :: Python :: 3.10
Classifier: License :: OSI Approved :: Apache Software License
Requires-Python: >=3.7
License-File: LICENSE
Requires-Dist: fastcore
Requires-Dist: pandas (>=1.5)
Requires-Dist: yFinance (>=0.1.77)
Requires-Dist: html5lib (>=1.1)
Requires-Dist: BeautifulSoup4 (>=4.11.1)
Provides-Extra: dev
